{
	"info": {
		"_postman_id": "476611a0-33d1-4079-81d4-9d5e49b1c074",
		"name": "LibraryTestTask",
		"schema": "https://schema.getpostman.com/json/collection/v2.1.0/collection.json",
		"_exporter_id": "20555670"
	},
	"item": [
		{
			"name": "Author",
			"item": [
				{
					"name": "Add author",
					"event": [
						{
							"listen": "test",
							"script": {
								"exec": [
									"pm.test(\"Status code is 201\", function () {",
									"    pm.expect(pm.response.code).to.be.equal(201);",
									"});"
								],
								"type": "text/javascript"
							}
						}
					],
					"request": {
						"method": "POST",
						"header": [],
						"body": {
							"mode": "raw",
							"raw": "{\n    \"name\": \"author 1\"\n}",
							"options": {
								"raw": {
									"language": "json"
								}
							}
						},
						"url": {
							"raw": "{{base_url}}/author",
							"host": [
								"{{base_url}}"
							],
							"path": [
								"author"
							]
						}
					},
					"response": []
				},
				{
					"name": "Add author noname",
					"event": [
						{
							"listen": "test",
							"script": {
								"exec": [
									"pm.test(\"Status code is 201\", function () {",
									"    pm.expect(pm.response.code).to.be.equal(201);",
									"});"
								],
								"type": "text/javascript"
							}
						}
					],
					"request": {
						"method": "POST",
						"header": [],
						"body": {
							"mode": "raw",
							"raw": "{\n    \"name\": \"noname\"\n}",
							"options": {
								"raw": {
									"language": "json"
								}
							}
						},
						"url": {
							"raw": "{{base_url}}/author",
							"host": [
								"{{base_url}}"
							],
							"path": [
								"author"
							]
						}
					},
					"response": []
				},
				{
					"name": "Add author 3",
					"event": [
						{
							"listen": "test",
							"script": {
								"exec": [
									"pm.test(\"Status code is 201\", function () {",
									"    pm.expect(pm.response.code).to.be.equal(201);",
									"});"
								],
								"type": "text/javascript"
							}
						}
					],
					"request": {
						"method": "POST",
						"header": [],
						"body": {
							"mode": "raw",
							"raw": "{\n    \"name\": \"author 3\"\n}",
							"options": {
								"raw": {
									"language": "json"
								}
							}
						},
						"url": {
							"raw": "{{base_url}}/author",
							"host": [
								"{{base_url}}"
							],
							"path": [
								"author"
							]
						}
					},
					"response": []
				},
				{
					"name": "Rename author",
					"event": [
						{
							"listen": "test",
							"script": {
								"exec": [
									"pm.test(\"Status code is 200\", function () {",
									"    pm.expect(pm.response.code).to.be.equal(200);",
									"});"
								],
								"type": "text/javascript"
							}
						}
					],
					"request": {
						"method": "PATCH",
						"header": [],
						"body": {
							"mode": "raw",
							"raw": "{\n    \"name\": \"noname changed\"\n}",
							"options": {
								"raw": {
									"language": "json"
								}
							}
						},
						"url": {
							"raw": "{{base_url}}/author/2",
							"host": [
								"{{base_url}}"
							],
							"path": [
								"author",
								"2"
							]
						}
					},
					"response": []
				},
				{
					"name": "Get list author without params",
					"event": [
						{
							"listen": "test",
							"script": {
								"exec": [
									"pm.test(\"Status code is 200\", function () {",
									"    pm.expect(pm.response.code).to.be.equal(200);",
									"});"
								],
								"type": "text/javascript"
							}
						}
					],
					"request": {
						"method": "GET",
						"header": [],
						"url": {
							"raw": "{{baseUrl}}/author",
							"host": [
								"{{baseUrl}}"
							],
							"path": [
								"author"
							]
						}
					},
					"response": []
				},
				{
					"name": "Get list author by text",
					"event": [
						{
							"listen": "test",
							"script": {
								"exec": [
									"pm.test(\"Status code is 200\", function () {",
									"    pm.expect(pm.response.code).to.be.equal(200);",
									"});"
								],
								"type": "text/javascript"
							}
						}
					],
					"request": {
						"method": "GET",
						"header": [],
						"url": {
							"raw": "{{baseUrl}}/author?text=thor",
							"host": [
								"{{baseUrl}}"
							],
							"path": [
								"author"
							],
							"query": [
								{
									"key": "text",
									"value": "thor"
								}
							]
						}
					},
					"response": []
				},
				{
					"name": "Delete author",
					"event": [
						{
							"listen": "test",
							"script": {
								"exec": [
									"pm.test(\"Status code is 204\", function () {",
									"    pm.expect(pm.response.code).to.be.equal(204);",
									"});"
								],
								"type": "text/javascript"
							}
						}
					],
					"request": {
						"method": "DELETE",
						"header": [],
						"body": {
							"mode": "raw",
							"raw": "",
							"options": {
								"raw": {
									"language": "json"
								}
							}
						},
						"url": {
							"raw": "{{base_url}}/author/3",
							"host": [
								"{{base_url}}"
							],
							"path": [
								"author",
								"3"
							]
						}
					},
					"response": []
				}
			]
		},
		{
			"name": "Book",
			"item": [
				{
					"name": "Add book",
					"event": [
						{
							"listen": "test",
							"script": {
								"exec": [
									"pm.test(\"Status code is 201\", function () {",
									"    pm.expect(pm.response.code).to.be.equal(201);",
									"});"
								],
								"type": "text/javascript"
							}
						}
					],
					"request": {
						"method": "POST",
						"header": [],
						"body": {
							"mode": "raw",
							"raw": "{\n    \"name\": \"book 1\",\n    \"isbn\": 1,\n    \"authorId\": 1\n}",
							"options": {
								"raw": {
									"language": "json"
								}
							}
						},
						"url": {
							"raw": "{{base_url}}/book",
							"host": [
								"{{base_url}}"
							],
							"path": [
								"book"
							]
						}
					},
					"response": []
				},
				{
					"name": "Add book 2",
					"event": [
						{
							"listen": "test",
							"script": {
								"exec": [
									"pm.test(\"Status code is 201\", function () {",
									"    pm.expect(pm.response.code).to.be.equal(201);",
									"});"
								],
								"type": "text/javascript"
							}
						}
					],
					"request": {
						"method": "POST",
						"header": [],
						"body": {
							"mode": "raw",
							"raw": "{\n    \"name\": \"adventure\",\n    \"isbn\": 2,\n    \"authorId\": 1\n}",
							"options": {
								"raw": {
									"language": "json"
								}
							}
						},
						"url": {
							"raw": "{{base_url}}/book",
							"host": [
								"{{base_url}}"
							],
							"path": [
								"book"
							]
						}
					},
					"response": []
				},
				{
					"name": "Rename book",
					"event": [
						{
							"listen": "test",
							"script": {
								"exec": [
									"pm.test(\"Status code is 200\", function () {",
									"    pm.expect(pm.response.code).to.be.equal(200);",
									"});"
								],
								"type": "text/javascript"
							}
						}
					],
					"request": {
						"method": "PATCH",
						"header": [],
						"body": {
							"mode": "raw",
							"raw": "{\n    \"name\": \"book renamed\"\n}",
							"options": {
								"raw": {
									"language": "json"
								}
							}
						},
						"url": {
							"raw": "{{base_url}}/book/1",
							"host": [
								"{{base_url}}"
							],
							"path": [
								"book",
								"1"
							]
						}
					},
					"response": []
				},
				{
					"name": "Change author",
					"event": [
						{
							"listen": "test",
							"script": {
								"exec": [
									"pm.test(\"Status code is 200\", function () {",
									"    pm.expect(pm.response.code).to.be.equal(200);",
									"});"
								],
								"type": "text/javascript"
							}
						}
					],
					"request": {
						"method": "PATCH",
						"header": [],
						"body": {
							"mode": "raw",
							"raw": "{\n    \"authorId\": 2\n}",
							"options": {
								"raw": {
									"language": "json"
								}
							}
						},
						"url": {
							"raw": "{{base_url}}/book/1",
							"host": [
								"{{base_url}}"
							],
							"path": [
								"book",
								"1"
							]
						}
					},
					"response": []
				},
				{
					"name": "Change isbn",
					"event": [
						{
							"listen": "test",
							"script": {
								"exec": [
									"pm.test(\"Status code is 200\", function () {",
									"    pm.expect(pm.response.code).to.be.equal(200);",
									"});"
								],
								"type": "text/javascript"
							}
						}
					],
					"request": {
						"method": "PATCH",
						"header": [],
						"body": {
							"mode": "raw",
							"raw": "{\n    \"isbn\": 3\n}",
							"options": {
								"raw": {
									"language": "json"
								}
							}
						},
						"url": {
							"raw": "{{base_url}}/book/1",
							"host": [
								"{{base_url}}"
							],
							"path": [
								"book",
								"1"
							]
						}
					},
					"response": []
				},
				{
					"name": "Get list book without params",
					"event": [
						{
							"listen": "test",
							"script": {
								"exec": [
									"pm.test(\"Status code is 200\", function () {",
									"    pm.expect(pm.response.code).to.be.equal(200);",
									"});"
								],
								"type": "text/javascript"
							}
						}
					],
					"request": {
						"method": "GET",
						"header": [],
						"url": {
							"raw": "{{baseUrl}}/book",
							"host": [
								"{{baseUrl}}"
							],
							"path": [
								"book"
							]
						}
					},
					"response": []
				},
				{
					"name": "Get list book by text",
					"event": [
						{
							"listen": "test",
							"script": {
								"exec": [
									"pm.test(\"Status code is 200\", function () {",
									"    pm.expect(pm.response.code).to.be.equal(200);",
									"});"
								],
								"type": "text/javascript"
							}
						}
					],
					"request": {
						"method": "GET",
						"header": [],
						"url": {
							"raw": "{{baseUrl}}/book?text=nture",
							"host": [
								"{{baseUrl}}"
							],
							"path": [
								"book"
							],
							"query": [
								{
									"key": "text",
									"value": "nture"
								}
							]
						}
					},
					"response": []
				},
				{
					"name": "Get list book by isbn",
					"event": [
						{
							"listen": "test",
							"script": {
								"exec": [
									"pm.test(\"Status code is 200\", function () {",
									"    pm.expect(pm.response.code).to.be.equal(200);",
									"});"
								],
								"type": "text/javascript"
							}
						}
					],
					"request": {
						"method": "GET",
						"header": [],
						"url": {
							"raw": "{{baseUrl}}/book?isbn=2",
							"host": [
								"{{baseUrl}}"
							],
							"path": [
								"book"
							],
							"query": [
								{
									"key": "isbn",
									"value": "2"
								}
							]
						}
					},
					"response": []
				},
				{
					"name": "Get list book by author",
					"event": [
						{
							"listen": "test",
							"script": {
								"exec": [
									"pm.test(\"Status code is 200\", function () {",
									"    pm.expect(pm.response.code).to.be.equal(200);",
									"});"
								],
								"type": "text/javascript"
							}
						}
					],
					"request": {
						"method": "GET",
						"header": [],
						"url": {
							"raw": "{{baseUrl}}/book?authorid=2",
							"host": [
								"{{baseUrl}}"
							],
							"path": [
								"book"
							],
							"query": [
								{
									"key": "authorid",
									"value": "2"
								}
							]
						}
					},
					"response": []
				},
				{
					"name": "Get list book by author and text",
					"event": [
						{
							"listen": "test",
							"script": {
								"exec": [
									"pm.test(\"Status code is 200\", function () {",
									"    pm.expect(pm.response.code).to.be.equal(200);",
									"});"
								],
								"type": "text/javascript"
							}
						}
					],
					"request": {
						"method": "GET",
						"header": [],
						"url": {
							"raw": "{{baseUrl}}/book?authorid=2&text=renam",
							"host": [
								"{{baseUrl}}"
							],
							"path": [
								"book"
							],
							"query": [
								{
									"key": "authorid",
									"value": "2"
								},
								{
									"key": "text",
									"value": "renam"
								}
							]
						}
					},
					"response": []
				},
				{
					"name": "Delete author",
					"event": [
						{
							"listen": "test",
							"script": {
								"exec": [
									"pm.test(\"Status code is 204\", function () {",
									"    pm.expect(pm.response.code).to.be.equal(204);",
									"});"
								],
								"type": "text/javascript"
							}
						}
					],
					"request": {
						"method": "DELETE",
						"header": [],
						"body": {
							"mode": "raw",
							"raw": "",
							"options": {
								"raw": {
									"language": "json"
								}
							}
						},
						"url": {
							"raw": "{{base_url}}/book/2",
							"host": [
								"{{base_url}}"
							],
							"path": [
								"book",
								"2"
							]
						}
					},
					"response": []
				}
			]
		}
	],
	"event": [
		{
			"listen": "prerequest",
			"script": {
				"type": "text/javascript",
				"exec": [
					""
				]
			}
		},
		{
			"listen": "test",
			"script": {
				"type": "text/javascript",
				"exec": [
					""
				]
			}
		}
	],
	"variable": [
		{
			"key": "baseUrl",
			"value": "http://localhost:8080",
			"type": "string"
		}
	]
}